dkopt/__init__.py
dkopt/entry_point.py
dkopt/exceptions.py
dkopt/card/__init__.py
dkopt/card/card.py
dkopt/card/deck.py
dkopt/card/hand.py
dkopt/search/__init__.py
dkopt/search/search.py
dkopt/search/setting.py
dkopt-0.0.4.dist-info/LICENSE
dkopt-0.0.4.dist-info/METADATA
dkopt-0.0.4.dist-info/WHEEL
dkopt-0.0.4.dist-info/top_level.txt
dkopt-0.0.4.dist-info/RECORD
