Metadata-Version: 2.1
Name: dkopt
Version: 0.0.4
Summary: deck-optimizer is a Python module to support TCG deck building.
Home-page: https://github.com/hasoya/deck-optimizer
Author: hasoya
Author-email: 20637498+hasoya@users.noreply.github.com
License: MIT
Platform: UNKNOWN
Classifier: Development Status :: 4 - Beta
Classifier: Intended Audience :: Developers
Classifier: Intended Audience :: End Users/Desktop
Classifier: Topic :: Games/Entertainment
Classifier: Topic :: Games/Entertainment :: Turn Based Strategy
Classifier: Programming Language :: Python
Classifier: Programming Language :: Python :: 3.7
Classifier: Programming Language :: Python :: 3.8
Classifier: Programming Language :: Python :: 3.9
Classifier: Programming Language :: Python :: 3.10
License-File: LICENSE
Requires-Dist: loguru (>=0.5)
Requires-Dist: pyyaml (>=5.0)
